lineless_table_rec/__init__.py
lineless_table_rec/main.py
lineless_table_rec/process.py
lineless_table_rec/utils.py
lineless_table_rec/utils_table_recover.py
lineless_table_rec/models/lore_detect.onnx
lineless_table_rec/models/lore_process.onnx
lineless_table_rec-3.8.dist-info/LICENSE
lineless_table_rec-3.8.dist-info/METADATA
lineless_table_rec-3.8.dist-info/WHEEL
lineless_table_rec-3.8.dist-info/entry_points.txt
lineless_table_rec-3.8.dist-info/top_level.txt
lineless_table_rec-3.8.dist-info/RECORD
