Metadata-Version: 2.1
Name: lineless-table-rec
Version: 3.8
Summary: Lineless Table Recognition
Home-page: https://github.com/RapidAI/TableStructureRec
Author: SWHL
Author-email: liekkaskono@163.com
License: Apache-2.0
Keywords: tsr,ocr,table-recognition
Platform: Any
Classifier: Programming Language :: Python :: 3.6
Classifier: Programming Language :: Python :: 3.7
Classifier: Programming Language :: Python :: 3.8
Classifier: Programming Language :: Python :: 3.9
Classifier: Programming Language :: Python :: 3.10
Classifier: Programming Language :: Python :: 3.11
Requires-Python: >=3.6,<3.12
Requires-Dist: numpy >=1.21.6
Requires-Dist: onnxruntime >=1.14.1
Requires-Dist: opencv-python
Requires-Dist: scipy
Requires-Dist: scikit-image
Requires-Dist: Shapely
Requires-Dist: rapidocr-onnxruntime >=1.3.8
